laurelin_cli/__init__.py
laurelin_cli/__main__.py
laurelin_cli/api_client.py
laurelin_cli/auth.py
laurelin_cli/cli.py
laurelin_cli/config.py
laurelin_cli-1.2.0.dist-info/licenses/LICENSE
laurelin_cli-1.2.0.dist-info/METADATA
laurelin_cli-1.2.0.dist-info/WHEEL
laurelin_cli-1.2.0.dist-info/entry_points.txt
laurelin_cli-1.2.0.dist-info/top_level.txt
laurelin_cli-1.2.0.dist-info/RECORD
